<?xml version="1.0" encoding="UTF-8"?>
<!-- edited with XMLSpy v2010 (http://www.altova.com) by ericke (ericke) -->
<ContractRoot>
	<TcpCont>
		<TransactionID>6001020001201006291000008902</TransactionID>
		<ActionCode>0</ActionCode>
		<BusCode>待定</BusCode>
		<ServiceCode>SVC30113</ServiceCode>
		<ServiceContractVer>SVC1100120100501</ServiceContractVer>
		<ServiceLevel>09</ServiceLevel>
		<SrcOrgID>100000</SrcOrgID>
		<SrcSysID>1000000001</SrcSysID>
		<SrcSysSign>1000000002</SrcSysSign>
		<DstOrgID>600305</DstOrgID>
		<DstSysID>6003050001</DstSysID>
		<ReqTime>20101213121212</ReqTime>
	</TcpCont>
	<SvcCont>
		<!--客户订单-->
		<SOO type="ADD_CUSTOMER_ORDER_REQ_TYPE">
			<!--查询公共请求消息-->
			<PUB_REQ>
				<!--标准对象操作ID,必填-->
				<SOO_ID>1234012</SOO_ID>
			</PUB_REQ>
			<!--客户订单对象-->
			<CUSTOMER_ORDER>
				<!--客户订单标识，必填-->
				<CUST_ORDER_ID>$-1001$</CUST_ORDER_ID>
				<!--客户标识，必填-->
				<CUST_ID>:getCustIdByAccNbr(区号，手机号码)</CUST_ID>
				<!--员工标识，可填-->
				<STAFF_ID>员工标识</STAFF_ID>
				<!--预受理标志，必填-->
				<PRE_HANDLE_FLAG>预受理标志</PRE_HANDLE_FLAG>
				<!--优先级，可填-->
				<PRIORITY>优先级</PRIORITY>
				<!--备注，可填-->
				<REMARKS>备注</REMARKS>
				<!--来源标识，必填-->
				<SOURCE_ID>来源标识</SOURCE_ID>
				<!--受理时间，可填-->
				<ACCEPT_TIME>受理时间</ACCEPT_TIME>
				<!--外部客户订单标识，可填-->
				<EXT_CUST_ORDER_ID>外部客户订单标识</EXT_CUST_ORDER_ID>
				<!--归属本地网标识，必填-->
				<LAN_ID>归属本地网标识</LAN_ID>				
			</CUSTOMER_ORDER>
		</SOO>
		<!--客户订单扩展属性，最多包括20个客户订单扩展属性对象-->
		<SOO type="SAVE_ORDER_ATTR_REQ_TYPE">
			<!--查询公共请求消息-->
			<PUB_REQ>
				<!--请求ID,必填-->
				<SOO_ID>1234013</SOO_ID>
			</PUB_REQ>
			<!--客户订单属性对象-->
			<ORDER_ATTR>
				<!--客户订单标识,必填-->
				<CUST_ORDER_ID>$-1001$</CUST_ORDER_ID>
				<!--属性规格CD，必填-->
				<ATTR_CD>属性规格CD</ATTR_CD>
				<!--属性规格名称，可填-->
				<ATTR_NAME>属性规格名称</ATTR_NAME>
				<!--属性值，必填-->
				<ATTR_VALUE>属性值</ATTR_VALUE>
			</ORDER_ATTR>
			<!--客户订单属性对象-->
			<ORDER_ATTR>
				<!--客户订单标识,必填-->
				<CUST_ORDER_ID>$-1001$</CUST_ORDER_ID>
				<!--属性规格CD，必填-->
				<ATTR_CD>属性规格CD</ATTR_CD>
				<!--属性规格名称，可填-->
				<ATTR_NAME>属性规格名称</ATTR_NAME>
				<!--属性值，必填-->
				<ATTR_VALUE>属性值</ATTR_VALUE>
			</ORDER_ATTR>
		</SOO>
		<!--客户订单联系人，最多包括20个客户订单联系人对象-->
		<SOO type="SAVE_ORDER_CONTACT_INFO_REQ_TYPE">
			<!--查询公共请求消息-->
			<PUB_REQ>
				<!--请求ID,必填-->
				<SOO_ID>1234014</SOO_ID>
			</PUB_REQ>
			<!--客户订单联系人信息-->
			<ORDER_CONTACT_INFO>
				<!--客户订单标识,必填-->
				<CUST_ORDER_ID>$-1001$</CUST_ORDER_ID>
				<!--联系人姓名，必填-->
				<CONTACT_NAME>联系人姓名</CONTACT_NAME>
				<!--联系人联系方式，必填-->
				<CONTACT_TYPE>联系人联系方式</CONTACT_TYPE>
				<!--联系号码，必填-->
				<CONTACT_NBR>联系号码</CONTACT_NBR>
			</ORDER_CONTACT_INFO>
			<!--客户订单联系人信息-->
			<ORDER_CONTACT_INFO>
				<!--客户订单标识,必填-->
				<CUST_ORDER_ID>$-1001$</CUST_ORDER_ID>
				<!--联系人姓名，必填-->
				<CONTACT_NAME>联系人姓名</CONTACT_NAME>
				<!--联系人联系方式，必填-->
				<CONTACT_TYPE>联系人联系方式</CONTACT_TYPE>
				<!--联系号码，必填-->
				<CONTACT_NBR>联系号码</CONTACT_NBR>
			</ORDER_CONTACT_INFO>
		</SOO>
		<!--客户订单经办人信息-->
		<SOO type="SAVE_CUST_ORDER_HANDLE_REQ_TYPE">
			<!--查询公共请求消息-->
			<PUB_REQ>
				<!--请求ID,必填-->
				<SOO_ID>1234015</SOO_ID>
			</PUB_REQ>
			<!--客户订单经办人信息-->
			<CUST_ORDER_HANDLE>
				<!--客户订单标识，必填-->
				<CUST_ORDER_ID>$-1001$</CUST_ORDER_ID>
				<!--经办人归属区号，可填-->
				<AREA_NBR>经办人归属区号</AREA_NBR>
				<!--经办人姓名，必填-->
				<HANDLE_PEOPLE_NAME>经办人姓名</HANDLE_PEOPLE_NAME>
				<!--经办人证件类型，必填-->
				<CERT_TYPE>经办人证件类型</CERT_TYPE>
				<!--经办人联系号码，必填-->
				<CONTACT_NBR>经办人联系号码</CONTACT_NBR>
			</CUST_ORDER_HANDLE>
		</SOO>
		<!--订单项分组-->
		<SOO type="ADD_ORDER_ITEM_GROUP_REQ_TYPE">
			<!--查询公共请求消息-->
			<PUB_REQ>
				<!--请求ID,必填-->
				<SOO_ID>1234016</SOO_ID>
			</PUB_REQ>
			<!--订单项分组-->
			<ORDER_ITEM>
				<!--订单项分组ID，必填-->
				<ORDER_ITEM_GROUP_ID>$-2001$</ORDER_ITEM_GROUP_ID>
				<!--客户订单标识，必填-->
				<CUST_ORDER_ID>$-1001$</CUST_ORDER_ID>
				<!--服务提供ID，必填-->
				<SERVICE_OFFER_ID>服务提供ID</SERVICE_OFFER_ID>
				<!--服务提供名称,可填-->
				<SERVICE_OFFER_NAME>服务提供名称</SERVICE_OFFER_NAME>
			</ORDER_ITEM>
		</SOO>
		<SOO type="DEL_PROD_OFFER_INST_REQ_TYPE">
			<!--查询公共请求消息-->
			<PUB_REQ>
				<!--请求ID,必填-->
				<SOO_ID>1234017</SOO_ID>
			</PUB_REQ>
			<!--订单通用输入-->
			<ORDER_REQ>
				<!--订单项分组ID，必填-->
				<ORDER_ITEM_GROUP_ID>$-2001$</ORDER_ITEM_GROUP_ID>
			</ORDER_REQ>
			<!--销售品实例ID，必填-->
			<PROD_OFFER_INST_ID>:getProdOfferInstIdByAccNbr(区号，手机号码，销售品标准编码)</PROD_OFFER_INST_ID>
		</SOO>
		<!--销售品实例-->
		<SOO type="ADD_PROD_OFFER_INST_REQ_TYPE">
			<!--查询公共请求消息-->
			<PUB_REQ>
				<!--请求ID,必填-->
				<SOO_ID>1234018</SOO_ID>
			</PUB_REQ>
			<!--订单通用输入-->
			<ORDER_REQ>
				<!--订单项分组ID,必填-->
				<ORDER_ITEM_GROUP_ID>$-2001$</ORDER_ITEM_GROUP_ID>
			</ORDER_REQ>
			<!--销售品实例-->
			<PROD_OFFER_INST>
				<!--销售品实例ID,必填-->
				<PROD_OFFER_INST_ID>$-3001$</PROD_OFFER_INST_ID>
				<!--外部销售品实例标识，可填-->
				<PROD_OFFER_INST_ID>外部销售品实例标识</PROD_OFFER_INST_ID>
				<!--客户标识，必填-->
				<CUST_ID>:getCustIdByAccNbr(区号，手机号码)</CUST_ID>
				<!--销售品ID，可填-->
				<PROD_OFFER_ID>销售品ID</PROD_OFFER_ID>
				<!--销售品名称，可填-->
				<PROD_OFFER_NAME>销售品名称</PROD_OFFER_NAME>
				<!--销售品集团统一编码，必填-->
				<PROD_OFFER_CODE>销售品集团统一编码</PROD_OFFER_CODE>
				<!--归属本地网标识，必填-->
				<LAN_ID>归属本地网标识</LAN_ID>
			</PROD_OFFER_INST>
		</SOO>
		<!--销售品产品实例关联关系-->
		<SOO type="ADD_OFFER_PROD_INST_REL_REQ_TYPE">
			<!--查询公共请求消息-->
			<PUB_REQ>
				<!--请求ID,必填-->
				<SOO_ID>1234019</SOO_ID>
			</PUB_REQ>
			<!--订单通用输入-->
			<ORDER_REQ>
				<!--订单项分组ID,必填-->
				<ORDER_ITEM_GROUP_ID>$-2001$</ORDER_ITEM_GROUP_ID>
			</ORDER_REQ>
			<!--销售品产品实例关联-->
			<OFFER_PROD_INST_REL>
				<!--产品实例ID,必填-->
				<PROD_INST_ID>:getProdInstIdByAccNbr(区号，手机号码)</PROD_INST_ID>
				<!--销售品实例ID，必填-->
				<PROD_OFFER_INST_ID>$-3001$</PROD_OFFER_INST_ID>
				<!--角色CD,可填-->
				<ROLE_CD>角色CD</ROLE_CD>
				<!--角色名称，可填-->
				<ROLE_NAME>角色名称</ROLE_NAME>
			</OFFER_PROD_INST_REL>
		</SOO>
	</SvcCont>
</ContractRoot>
